AUTHORS
LICENSE
MANIFEST.in
README.rst
setup.py
django_sorter.egg-info/PKG-INFO
django_sorter.egg-info/SOURCES.txt
django_sorter.egg-info/dependency_links.txt
django_sorter.egg-info/requires.txt
django_sorter.egg-info/top_level.txt
sorter/__init__.py
sorter/conf.py
sorter/models.py
sorter/test_settings.py
sorter/tests.py
sorter/utils.py
sorter/locale/de/LC_MESSAGES/django.mo
sorter/locale/de/LC_MESSAGES/django.po
sorter/locale/en/LC_MESSAGES/django.mo
sorter/locale/en/LC_MESSAGES/django.po
sorter/templates/sorter/sortform.html
sorter/templates/sorter/sortlink.html
sorter/templatetags/__init__.py
sorter/templatetags/sorter_tags.py